mexca/__init__.py
mexca/container.py
mexca/data.py
mexca/pipeline.py
mexca/utils.py
mexca/audio/__init__.py
mexca/audio/extraction.py
mexca/audio/identification.py
mexca/text/__init__.py
mexca/text/sentiment.py
mexca/text/transcription.py
mexca/video/__init__.py
mexca/video/anfl.py
mexca/video/extraction.py
mexca/video/helper_classes.py
mexca/video/mefarg.py
mexca/video/mefl.py
mexca-1.0.4.dist-info/LICENSE
mexca-1.0.4.dist-info/METADATA
mexca-1.0.4.dist-info/NOTICE
mexca-1.0.4.dist-info/WHEEL
mexca-1.0.4.dist-info/entry_points.txt
mexca-1.0.4.dist-info/top_level.txt
mexca-1.0.4.dist-info/RECORD
