Metadata-Version: 2.1
Name: mexca
Version: 1.0.4
Summary: Emotion expression capture from multiple modalities.
Home-page: https://github.com/mexca/mexca
Author: Malte Luken
Author-email: m.luken@esciencecenter.nl
Project-URL: Bug Tracker, https://github.com/mexca/mexca/issues
Keywords: emotion,multimodal,expression
Classifier: Development Status :: 5 - Production/Stable
Classifier: Intended Audience :: Science/Research
Classifier: License :: OSI Approved :: Apache Software License
Classifier: Natural Language :: English
Classifier: Programming Language :: Python :: 3.8
Classifier: Programming Language :: Python :: 3.9
Classifier: Programming Language :: Python :: 3.10
Requires-Python: <3.11,>3.7
License-File: LICENSE
License-File: NOTICE
Requires-Dist: docker >=6.0.1
Requires-Dist: intervaltree >=3.1.0
Requires-Dist: moviepy >=1.0.3
Requires-Dist: numpy <1.24,>=1.21
Requires-Dist: polars ==0.19.8
Requires-Dist: pydantic ==2.4.2
Requires-Dist: pyyaml >=6.0
Requires-Dist: scipy >=1.7.3
Requires-Dist: srt >=3.5.2
Requires-Dist: tqdm >=4.64.0
Provides-Extra: all
Requires-Dist: mexca[sen,spe,tra,vid,voi] ; extra == 'all'
Provides-Extra: demo
Requires-Dist: ipywidgets ; extra == 'demo'
Requires-Dist: notebook ; extra == 'demo'
Provides-Extra: dev
Requires-Dist: black ; extra == 'dev'
Requires-Dist: bump2version ; extra == 'dev'
Requires-Dist: prospector[with_pyroma] ==1.7.7 ; extra == 'dev'
Requires-Dist: pre-commit ; extra == 'dev'
Requires-Dist: pylint ==2.15.6 ; extra == 'dev'
Requires-Dist: isort ; extra == 'dev'
Requires-Dist: pytest ; extra == 'dev'
Requires-Dist: pytest-cov ; extra == 'dev'
Requires-Dist: sphinx ; extra == 'dev'
Requires-Dist: sphinx-rtd-theme ; extra == 'dev'
Requires-Dist: sphinx-autoapi ; extra == 'dev'
Requires-Dist: tox ; extra == 'dev'
Requires-Dist: myst-parser ; extra == 'dev'
Provides-Extra: publishing
Requires-Dist: twine ; extra == 'publishing'
Requires-Dist: wheel ; extra == 'publishing'
Provides-Extra: sen
Requires-Dist: accelerate ==0.18.0 ; extra == 'sen'
Requires-Dist: bitsandbytes ==0.38.1 ; extra == 'sen'
Requires-Dist: protobuf ==3.20 ; extra == 'sen'
Requires-Dist: sentencepiece ; extra == 'sen'
Requires-Dist: torch >=2.0 ; extra == 'sen'
Requires-Dist: transformers ==4.25.1 ; extra == 'sen'
Provides-Extra: spe
Requires-Dist: pyannote.audio ==3.1.1 ; extra == 'spe'
Requires-Dist: pyannote.core >=5.0 ; extra == 'spe'
Requires-Dist: torch >=2.0 ; extra == 'spe'
Provides-Extra: tra
Requires-Dist: openai-whisper ; extra == 'tra'
Requires-Dist: torch >=2.0 ; extra == 'tra'
Requires-Dist: transformers ==4.25.1 ; extra == 'tra'
Provides-Extra: vid
Requires-Dist: facenet-pytorch ==2.5.3 ; extra == 'vid'
Requires-Dist: av ==10.0 ; extra == 'vid'
Requires-Dist: huggingface-hub ==0.17.3 ; extra == 'vid'
Requires-Dist: scikit-learn ==1.3.1 ; extra == 'vid'
Requires-Dist: spectralcluster ==0.2.16 ; extra == 'vid'
Requires-Dist: torch >=2.0 ; extra == 'vid'
Provides-Extra: voi
Requires-Dist: emvoice ; extra == 'voi'
Requires-Dist: librosa <0.10.0 ; extra == 'voi'
